yakmerge/__init__.py
yakmerge/__main__.py
yakindu_merge_py-0.0.2.dist-info/LICENSE
yakindu_merge_py-0.0.2.dist-info/METADATA
yakindu_merge_py-0.0.2.dist-info/WHEEL
yakindu_merge_py-0.0.2.dist-info/entry_points.txt
yakindu_merge_py-0.0.2.dist-info/top_level.txt
yakindu_merge_py-0.0.2.dist-info/RECORD
