Metadata-Version: 2.1
Name: yakindu-merge-py
Version: 0.0.2
Summary: Divide and merge statecharts for easy collaboration
Author-email: Rein Spanjer <contact@reinspanjer.nl>
License: MIT License
Project-URL: Homepage, https://github.com/Spanjer1/yakindu-merge-py
Keywords: yakindu,tool,merge
Classifier: License :: OSI Approved :: MIT License
Classifier: Programming Language :: Python
Classifier: Programming Language :: Python :: 3
Requires-Python: >=3.6
License-File: LICENSE
Requires-Dist: lxml (==4.9.1)
Requires-Dist: tomli ; python_version < "3.11"
Provides-Extra: dev
Requires-Dist: black ; extra == 'dev'
Requires-Dist: pip-tools ; extra == 'dev'
Requires-Dist: pytest ; extra == 'dev'
